lazytransform.py
lazytransform-1.18.dist-info/LICENSE
lazytransform-1.18.dist-info/METADATA
lazytransform-1.18.dist-info/WHEEL
lazytransform-1.18.dist-info/top_level.txt
lazytransform-1.18.dist-info/RECORD
