Metadata-Version: 2.2
Name: lazytransform
Version: 1.18
Summary: Clean your data using a scikit-learn transformer in a single line of code
Home-page: https://github.com/AutoViML/lazytransform
Author: Ram Seshadri
License: Apache License 2.0
Classifier: Programming Language :: Python :: 3
Classifier: Operating System :: OS Independent
License-File: LICENSE
Requires-Dist: numpy<2.0
Requires-Dist: pandas>=1.2.4
Requires-Dist: scipy
Requires-Dist: scikit-learn>=1.2.2
Requires-Dist: python-dateutil>=2.8.1
Requires-Dist: lightgbm>=3.2.1
Requires-Dist: matplotlib>=3.4.2
Requires-Dist: category-encoders>=2.6.2
Requires-Dist: tqdm>=4.61.1
Requires-Dist: xgboost>=1.6
Dynamic: author
Dynamic: classifier
Dynamic: description
Dynamic: description-content-type
Dynamic: home-page
Dynamic: license
Dynamic: requires-dist
Dynamic: summary
